clcmo_game-0.1.1.dist-info/licenses/LICENCE
controllers/__init__.py
controllers/game_controller.py
controllers/input_handler.py
locales/__init__.py
models/__init__.py
models/enemy.py
models/game_state.py
models/hero.py
models/level.py
views/__init__.py
views/base_view.py
views/game_view.py
views/hud_view.py
views/menu_view.py
views/pause_view.py
clcmo_game-0.1.1.dist-info/METADATA
clcmo_game-0.1.1.dist-info/WHEEL
clcmo_game-0.1.1.dist-info/top_level.txt
clcmo_game-0.1.1.dist-info/RECORD
