Metadata-Version: 2.4
Name: clcmo-game
Version: 0.1.1
Summary: A description of your game
Requires-Python: >=3.11
License-File: LICENCE
Requires-Dist: pgzero>=1.2.1
Requires-Dist: pygame>=2.6.1
Dynamic: license-file
